Metadata-Version: 1.2
Name: llvm-minusminus-emulator
Version: 1.1.0
Summary: A simple hacky emulator/debugger for LLVM--
Home-page: https://gitlab.com/cfreksen/llvm--emulator
Author: Casper Freksen
Author-email: cfreksen@cs.au.dk
License: GPLv3+
Keywords: llvm debugger
Platform: UNKNOWN
Classifier: Development Status :: 4 - Beta
Classifier: Topic :: System :: Emulators
Classifier: Topic :: Software Development :: Debuggers
Classifier: Intended Audience :: Education
Classifier: Intended Audience :: Developers
Classifier: License :: OSI Approved :: GNU General Public License v3 or later (GPLv3+)
Classifier: Natural Language :: English
Classifier: Programming Language :: Python :: 3 :: Only
Classifier: Programming Language :: Python :: 3.5
Classifier: Programming Language :: Python :: 3.6
Classifier: Environment :: Console
Requires-Python: ~=3.5
